serde/__init__.py
serde/byteline.py
serde/csv.py
serde/helper.py
serde/jl.py
serde/json.py
serde/pickle.py
serde/prelude.py
serde/textline.py
serde/yaml.py
serde2-1.9.2.dist-info/LICENSE
serde2-1.9.2.dist-info/METADATA
serde2-1.9.2.dist-info/WHEEL
serde2-1.9.2.dist-info/RECORD
